AUTHORS
CHANGELOG.txt
DESCRIPTION
LICENSE
MANIFEST.in
README.rst
setup.py
django_generic_positions.egg-info/PKG-INFO
django_generic_positions.egg-info/SOURCES.txt
django_generic_positions.egg-info/dependency_links.txt
django_generic_positions.egg-info/top_level.txt
generic_positions/__init__.py
generic_positions/admin.py
generic_positions/models.py
generic_positions/urls.py
generic_positions/views.py
generic_positions/migrations/0001_initial.py
generic_positions/migrations/__init__.py
generic_positions/south_migrations/0001_initial.py
generic_positions/south_migrations/__init__.py
generic_positions/static/generic_positions/js/reorder.js
generic_positions/templates/generic_positions/position.html
generic_positions/templates/generic_positions/admin/change_list.html
generic_positions/templatetags/__init__.py
generic_positions/templatetags/position_tags.py
generic_positions/tests/__init__.py
generic_positions/tests/models_tests.py
generic_positions/tests/settings.py
generic_positions/tests/tags_tests.py
generic_positions/tests/test_settings.py
generic_positions/tests/urls.py
generic_positions/tests/integration_tests/__init__.py
generic_positions/tests/integration_tests/views_tests.py
generic_positions/tests/test_app/__init__.py
generic_positions/tests/test_app/admin.py
generic_positions/tests/test_app/models.py
generic_positions/tests/test_app/templates/404.html
generic_positions/tests/test_app/templates/base.html
generic_positions/tests/test_app/templates/test_app/dummymodel_list.html