Metadata-Version: 1.0
Name: django-generic-positions
Version: 0.2
Summary: Generic app for using a drag & drop position field, wherever you want to.
